LICENSE
README.md
setup.cfg
setup.py
velocity/__init__.py
velocity/__version__.py
velocity/velocity.py
velocity.egg-info/PKG-INFO
velocity.egg-info/SOURCES.txt
velocity.egg-info/dependency_links.txt
velocity.egg-info/not-zip-safe
velocity.egg-info/top_level.txt