Metadata-Version: 2.1
Name: velocity
Version: 0.0.1
Summary: DNS caching for humans
Home-page: https://github.com/s0md3v/velocity
Author: Somdev Sangwan
Author-email: s0md3v@gmail.com
License: UNKNOWN
Project-URL: Source, https://github.com/s0md3v/velocity
Platform: UNKNOWN
Classifier: Development Status :: 5 - Production/Stable
Classifier: Intended Audience :: Developers
Classifier: Natural Language :: English
Classifier: License :: OSI Approved :: GNU General Public License v3 (GPLv3)
Classifier: Programming Language :: Python
Classifier: Programming Language :: Python :: 2
Classifier: Programming Language :: Python :: 3
Requires-Python: >=2.7
